odoo/addons/cooperator_eater/README.rst
odoo/addons/cooperator_eater/__init__.py
odoo/addons/cooperator_eater/__manifest__.py
odoo/addons/cooperator_eater/demo/product_share.xml
odoo/addons/cooperator_eater/i18n/cooperator_eater.pot
odoo/addons/cooperator_eater/i18n/fr.po
odoo/addons/cooperator_eater/models/__init__.py
odoo/addons/cooperator_eater/models/product_template.py
odoo/addons/cooperator_eater/models/res_partner.py
odoo/addons/cooperator_eater/models/subscription_request.py
odoo/addons/cooperator_eater/readme/CONTRIBUTORS.rst
odoo/addons/cooperator_eater/readme/DESCRIPTION.rst
odoo/addons/cooperator_eater/static/description/index.html
odoo/addons/cooperator_eater/tests/__init__.py
odoo/addons/cooperator_eater/tests/test_eaters.py
odoo/addons/cooperator_eater/views/product_template_views.xml
odoo_addon_cooperator_eater-16.0.1.0.0.4.dist-info/METADATA
odoo_addon_cooperator_eater-16.0.1.0.0.4.dist-info/WHEEL
odoo_addon_cooperator_eater-16.0.1.0.0.4.dist-info/top_level.txt
odoo_addon_cooperator_eater-16.0.1.0.0.4.dist-info/RECORD
