Metadata-Version: 2.1
Name: odoo-addon-cooperator_eater
Version: 16.0.1.0.0.4
Requires-Python: >=3.10
Requires-Dist: odoo-addon-cooperator_worker>=16.0dev,<16.1dev
Requires-Dist: odoo-addon-eater>=16.0dev,<16.1dev
Requires-Dist: odoo-addon-partner_contact_birthdate>=16.0dev,<16.1dev
Requires-Dist: odoo>=16.0a,<16.1dev
Summary: Eater configuration based on Share product
Home-page: https://github.com/beescoop/Obeesdoo
License: AGPL-3
Author: BEES coop, Coop IT Easy SC
Classifier: Programming Language :: Python
Classifier: Framework :: Odoo
Classifier: Framework :: Odoo :: 16.0
Classifier: License :: OSI Approved :: GNU Affero General Public License v3
